[
  {
    "View": {
      "text": "View Submission",
      "href": "https://www.hktlora.com/wp-admin/post.php?action=edit&post=6190"
    },
    "Form ID": "New Form",
    "Email": "kazemv@gmail.com",
    "Read/Unread": "huakuantong2025-06-03 06:04",
    "Cloned": "",
    "Submitted On": "Quote",
    "Submission Date": "2025-06-03 12:12:48"
  },
  {
    "View": {
      "text": "View Submission",
      "href": "https://www.hktlora.com/wp-admin/post.php?action=edit&post=6189"
    },
    "Form ID": "New Form",
    "Email": "fabian@bellsolutions.com.my",
    "Read/Unread": "huakuantong2025-06-03 02:51",
    "Cloned": "",
    "Submitted On": "Quote",
    "Submission Date": "2025-06-03 10:46:31"
  },
  {
    "View": {
      "text": "View Submission",
      "href": "https://www.hktlora.com/wp-admin/post.php?action=edit&post=6188"
    },
    "Form ID": "New Form",
    "Email": "nabil@mimartools.com.sa",
    "Read/Unread": "huakuantong2025-06-03 02:52",
    "Cloned": "",
    "Submitted On": "Quote",
    "Submission Date": "2025-06-02 20:02:30"
  },
  {
    "View": {
      "text": "View Submission",
      "href": "https://www.hktlora.com/wp-admin/post.php?action=edit&post=6187"
    },
    "Form ID": "New Form",
    "Email": "sales@cattech.co.ke",
    "Read/Unread": "huakuantong2025-06-03 02:52",
    "Cloned": "",
    "Submitted On": "Contact",
    "Submission Date": "2025-06-02 16:47:33"
  },
  {
    "View": {
      "text": "View Submission",
      "href": "https://www.hktlora.com/wp-admin/post.php?action=edit&post=6186"
    },
    "Form ID": "New Form",
    "Email": "pradeeka.seneviratne@gmail.com",
    "Read/Unread": "huakuantong2025-06-03 02:52",
    "Cloned": "",
    "Submitted On": "Contact",
    "Submission Date": "2025-06-02 16:32:29"
  },
  {
    "View": {
      "text": "View Submission",
      "href": "https://www.hktlora.com/wp-admin/post.php?action=edit&post=6185"
    },
    "Form ID": "New Form",
    "Email": "glenn@ai4.co",
    "Read/Unread": "huakuantong2025-06-03 02:52",
    "Cloned": "",
    "Submitted On": "Contact",
    "Submission Date": "2025-06-02 16:18:19"
  },
  {
    "View": {
      "text": "View Submission",
      "href": "https://www.hktlora.com/wp-admin/post.php?action=edit&post=6184"
    },
    "Form ID": "New Form",
    "Email": "galindoc.rodrigo@gmail.com",
    "Read/Unread": "huakuantong2025-06-03 02:52",
    "Cloned": "",
    "Submitted On": "Quote",
    "Submission Date": "2025-06-02 15:07:23"
  },
  {
    "View": {
      "text": "View Submission",
      "href": "https://www.hktlora.com/wp-admin/post.php?action=edit&post=6183"
    },
    "Form ID": "New Form",
    "Email": "thebigbom223@gmail.com",
    "Read/Unread": "huakuantong2025-06-03 02:52",
    "Cloned": "",
    "Submitted On": "Quote",
    "Submission Date": "2025-06-02 12:41:42"
  },
  {
    "View": {
      "text": "View Submission",
      "href": "https://www.hktlora.com/wp-admin/post.php?action=edit&post=6182"
    },
    "Form ID": "New Form",
    "Email": "leilord@hotmail.com",
    "Read/Unread": "huakuantong2025-06-03 02:53",
    "Cloned": "",
    "Submitted On": "Contact",
    "Submission Date": "2025-06-02 10:06:07"
  },
  {
    "View": {
      "text": "View Submission",
      "href": "https://www.hktlora.com/wp-admin/post.php?action=edit&post=6181"
    },
    "Form ID": "New Form",
    "Email": "bernard@toi.co.za",
    "Read/Unread": "huakuantong2025-06-03 02:53",
    "Cloned": "",
    "Submitted On": "Quote",
    "Submission Date": "2025-06-01 04:15:01"
  },
  {
    "View": {
      "text": "View Submission",
      "href": "https://www.hktlora.com/wp-admin/post.php?action=edit&post=6180"
    },
    "Form ID": "New Form",
    "Email": "cayturk47@360.cn",
    "Read/Unread": "huakuantong2025-05-31 12:40",
    "Cloned": "",
    "Submitted On": "Home",
    "Submission Date": "2025-05-31 08:13:31"
  },
  {
    "View": {
      "text": "View Submission",
      "href": "https://www.hktlora.com/wp-admin/post.php?action=edit&post=6179"
    },
    "Form ID": "New Form",
    "Email": "heteclimited@gmail.com",
    "Read/Unread": "huakuantong2025-05-31 12:41",
    "Cloned": "",
    "Submitted On": "Contact",
    "Submission Date": "2025-05-31 00:24:13"
  },
  {
    "View": {
      "text": "View Submission",
      "href": "https://www.hktlora.com/wp-admin/post.php?action=edit&post=6178"
    },
    "Form ID": "New Form",
    "Email": "ezequiel.scheffer@semak.com.ar",
    "Read/Unread": "huakuantong2025-05-31 12:41",
    "Cloned": "",
    "Submitted On": "Quote",
    "Submission Date": "2025-05-30 21:19:13"
  },
  {
    "View": {
      "text": "View Submission",
      "href": "https://www.hktlora.com/wp-admin/post.php?action=edit&post=6177"
    },
    "Form ID": "New Form",
    "Email": "akm.hafiz@gmail.com",
    "Read/Unread": "huakuantong2025-05-31 12:42",
    "Cloned": "",
    "Submitted On": "Contact",
    "Submission Date": "2025-05-30 19:48:30"
  },
  {
    "View": {
      "text": "View Submission",
      "href": "https://www.hktlora.com/wp-admin/post.php?action=edit&post=6176"
    },
    "Form ID": "New Form",
    "Email": "longwind523@gmail.com",
    "Read/Unread": "huakuantong2025-05-30 08:50",
    "Cloned": "",
    "Submitted On": "Home",
    "Submission Date": "2025-05-30 16:35:19"
  },
  {
    "View": {
      "text": "View Submission",
      "href": "https://www.hktlora.com/wp-admin/post.php?action=edit&post=6175"
    },
    "Form ID": "New Form",
    "Email": "michael@centralbridgeconstruction.co.za",
    "Read/Unread": "huakuantong2025-05-30 06:27",
    "Cloned": "",
    "Submitted On": "Quote",
    "Submission Date": "2025-05-29 16:14:59"
  },
  {
    "View": {
      "text": "View Submission",
      "href": "https://www.hktlora.com/wp-admin/post.php?action=edit&post=6174"
    },
    "Form ID": "New Form",
    "Email": "brice.corrieu@unabiz.com",
    "Read/Unread": "huakuantong2025-05-30 06:27",
    "Cloned": "",
    "Submitted On": "Contact",
    "Submission Date": "2025-05-29 16:14:39"
  },
  {
    "View": {
      "text": "View Submission",
      "href": "https://www.hktlora.com/wp-admin/post.php?action=edit&post=6173"
    },
    "Form ID": "New Form",
    "Email": "imaxkie6324@gmail.com",
    "Read/Unread": "huakuantong2025-05-30 06:27",
    "Cloned": "",
    "Submitted On": "Quote",
    "Submission Date": "2025-05-29 14:06:28"
  },
  {
    "View": {
      "text": "View Submission",
      "href": "https://www.hktlora.com/wp-admin/post.php?action=edit&post=6172"
    },
    "Form ID": "New Form",
    "Email": "brendajeanfair@gmail.com",
    "Read/Unread": "huakuantong2025-05-30 06:27",
    "Cloned": "",
    "Submitted On": "Contact",
    "Submission Date": "2025-05-29 12:23:23"
  },
  {
    "View": {
      "text": "View Submission",
      "href": "https://www.hktlora.com/wp-admin/post.php?action=edit&post=6171"
    },
    "Form ID": "New Form",
    "Email": "tim@sqippa.com",
    "Read/Unread": "huakuantong2025-05-30 06:28",
    "Cloned": "",
    "Submitted On": "Quote",
    "Submission Date": "2025-05-28 18:29:59"
  }
]